setup.py
dnd_stats/BinomialDistribution.py
dnd_stats/Gaussiandistribution.py
dnd_stats/Generaldistribution.py
dnd_stats/__init__.py
dnd_stats.egg-info/PKG-INFO
dnd_stats.egg-info/SOURCES.txt
dnd_stats.egg-info/dependency_links.txt
dnd_stats.egg-info/not-zip-safe
dnd_stats.egg-info/requires.txt
dnd_stats.egg-info/top_level.txt