Metadata-Version: 1.0
Name: dnd-stats
Version: 0.2
Summary: Probability Distributions and Statistics Methods
Home-page: UNKNOWN
Author: Divy Pandya
Author-email: UNKNOWN
License: MIT
Platform: UNKNOWN
